{"ac650-32ap":{"org":"AC650-32AP_pic","img":["front.png","front_left.png","front_right.png","front_top.png","left.png","rear.png","rear_left.png","rear_right.png","rear_top.png","right.png"]},"ac650-64ap":{"org":"AC650-64AP_pic","img":["front.png","front_left.png","front_right.png","front_top.png","left.png","rear.png","rear_left.png","rear_right.png","rear_top.png","right.png"]},"ac6507s":{"org":"AC6507S_pic","img":["front.png","front_left.png","front_right.png","front_top.png","left.png","rear.png","rear_left.png","rear_right.png","rear_top.png","right.png","top.png"]},"ac6508":{"org":"AC6508_pic","img":["front.png","front_left.png","front_right.png","front_top.png","left.png","rear.png","rear_left.png","rear_right.png","rear_top.png","right.png","top.png"]},"ac6605":{"org":"AC6605_pic","img":["01-Front.png","02-Front_looking_down.png","03-Front_left 30°down 15°.png","04-Front_Right 30°down 15°.png","05-Left side.png","06-Right side.png","07-Rear.png","08-Rear_looking down.png","09-Nameplate.png","10-Rear_left 30°down 15°.png","11-Rear_right 30°down 15°.png"]},"ac6800v":{"org":"AC6800V_pic","img":["front.png","rear.png"]},"ac6805":{"org":"AC6805_pic","img":["front.png","front_right.png","front_top.png","left.png","rear.png","right.png"]},"ad9430dn-24":{"org":"AD9430DN-24_pic","img":["01.png","02.png","03.png","04.png","05.png","06.png","07.png"]},"ap1050dn-s":{"org":"AP1050DN-S_pic","img":["01.png","02.png","03.png","04.png","05.png","06.png","07.png"]},"ap2010dn":{"org":"AP2010DN_pic","img":["01.png","02.png","03.png","04.png","05.png","06.png"]},"ap2030dn-s":{"org":"AP2030DN-S_pic","img":["bottom.png","front_left.png","front_right.png","front_top.png","rear_top.png","right.png","stand_left.png","stand_right.png","top.png"]},"ap2050dn-e":{"org":"AP2050DN-E_pic","img":["01.png","02.png","03.png","04.png","05.png","06.png","07.png","08.png","09.png","10.png","11.png"]},"ap2050dn":{"org":"AP2050DN_pic","img":["01.png","02.png","03.png","04.png","05.png","06.png","07.png","08.png","09.png","10.png","11.png"]},"ap2051dn-l-s":{"org":"AP2051DN-L-S_pic","img":["01.png","02.png","03.png","04.png"]},"ap2051dn-s":{"org":"AP2051DN-S_pic","img":["bottom.png","front_left.png","front_right.png","front_top.png","rear.png","rear_top.png","right.png","stand_left.png","stand_right.png","top.png"]},"ap230":{"org":"AP230_pic","img":["bottom.png","front_left.png","front_right.png","front_top.png","rear_top.png","right.png","stand_left.png","stand_right.png","top.png"]},"ap3050de":{"org":"AP3050DE_pic","img":["01.png","02.png","03.png","04.png","05.png"]},"ap310":{"org":"AP310_pic","img":["front.png","front_left.png","front_right.png","front_top.png","top.png"]},"ap330":{"org":"AP330_pic","img":["front.png","front_left.png","front_right.png","front_top.png","top.png"]},"ap350":{"org":"AP350_pic","img":["bottom.png","front.png","front_left.png","front_right.png","rear_top.png","top.png"]},"ap4050de-b-s":{"org":"AP4050DE-B-S_pic","img":["01.png","02.png","03.png","04.png","05.png"]},"ap4050de-m-s":{"org":"AP4050DE-M-S_pic","img":["01.png","02.png","03.png","04.png","05.png"]},"ap4050de-m":{"org":"AP4050DE-M_pic","img":["01.png","02.png","03.png","04.png","05.png","06.png","07.png"]},"ap4050dn-e":{"org":"AP4050DN-E_pic","img":["01.png","02.png","03.png","04.png","05.png","06.png","07.png","08.png"]},"ap4050dn-s":{"org":"AP4050DN-S_pic","img":["01.png","02.png","03.png","04.png","05.png","06.png","07.png"]},"ap4050dn":{"org":"AP4050DN_pic","img":["01.png","02.png","03.png","04.png","05.png","06.png","07.png"]},"ap4051dn-s":{"org":"AP4051DN-S_pic","img":["01.png","02.png","03.png","04.png","05.png","06.png","07.png"]},"ap4051dn":{"org":"AP4051DN_pic","img":["02.png","03.png","04.png","05.png","06.png","07.png","1.png"]},"ap4051tn":{"org":"AP4051TN_pic","img":["bottom.png","front.png","front_left.png","front_right.png","rear_top.png","top.png"]},"ap5130dn":{"org":"AP5130DN_pic","img":["01.png","02.png","03.png","04.png","05.png"]},"ap5510-w-gp":{"org":"AP5510-W-GP_pic","img":["01-Front.png","02-Left.png","03-Bottom.png","05-Rear.png","06-Front_right_down.png","07-Rear_left_down.png"]},"ap6052dn":{"org":"AP6052DN_pic","img":["bottom.png","front.png","front_left.png","front_right.png","rear_top.png","top.png"]},"ap6510dn-agn":{"org":"AP6510DN-AGN_pic","img":["01.png","02.png","03.png","04.png","05.png","06.png","07.png","08.png","09.png","10.png","11.png","12.png","13.png","14.png","15.png"]},"ap7030de":{"org":"AP7030DE_pic","img":["01.png","02.png","03.png","04.png"]},"ap7050de":{"org":"AP7050DE_pic","img":["01.png","02.png","03.png","04.png","05.png","06.png"]},"ap7052dn":{"org":"AP7052DN_pic","img":["01.png","02.png","03.png","04.png","05.png","06.png","07.png","08.png","09.png"]},"ap7060dn":{"org":"AP7060DN_pic","img":["bottom.png","front.png","front_left.png","front_right.png","front_top.png","rear.png","rear_left.png","rear_top.png"]},"ap8050dn-s":{"org":"AP8050DN-S_pic","img":["bottom.png","front.png","front_left.png","front_right.png","front_top.png","rear.png","rear_bottom.png","right.png","top.png"]},"ap8050dn":{"org":"AP8050DN_pic","img":["01.png","02.png","03.png","04.png","05.png","06.png","07.png","08.png","09.png","10.png","11.png"]},"ap8050tn-hd":{"org":"AP8050TN-HD_pic","img":["bottom.png","front.png","front_left.png","front_right.png","front_top.png","left.png","rear.png","rear_top.png","right.png","top.png"]},"ar1220c-s":{"org":"AR1220C-S_pic","img":["front.png","front_left.png","front_right.png","front_top.png","rear.png","rear_top.png"]},"ar1220e":{"org":"AR1220E_pic","img":["front.png","front_left.png","front_right.png","front_top.png","rear.png","rear_left.png","rear_right.png","rear_top.png"]},"ar161ew":{"org":"AR161EW_pic","img":["01.png","02.png","03.png","04.png","05.png","06.png","07.png","08.png","09.png","10.png","11.png"]},"ar2204-27ge-s":{"org":"AR2204-27GE-S_pic","img":["front.png","front_left.png","front_right.png","front_top.png","rear.png","rear_top.png"]},"ar2204-27ge":{"org":"AR2204-27GE_pic","img":["01.png","02.png","03.png","04.png","05.png","06.png","07.png","08.png","09.png","10.png","11.png"]},"ar301":{"org":"AR301_pic","img":["front_left.png","front_right.png","front_top.png","rear.png"]},"ar3260e-s":{"org":"AR3260E-S_pic","img":["front.png","front_left.png","front_right.png","front_top.png","rear.png","rear_left.png","rear_right.png","rear_top.png"]},"ar3260":{"org":"AR3260_pic","img":["front.png","front_left.png","front_right.png","front_top.png","rear.png","rear_left.png","rear_right.png","rear_top.png"]},"ar502cg-l":{"org":"AR502CG-L_pic","img":["front.png","front_left.png","front_right.png","front_top.png"]},"ar550-8fe-d-h":{"org":"AR550-8FE-D-H_pic","img":["01.png","02.png","03.png","04.png","05.png","06.png","07.png","08.png"]},"ar6120":{"org":"AR6120_pic","img":["front.png","front_left.png","front_right.png","front_top.png","rear.png"]},"ar6300-s":{"org":"AR6300-S_pic","img":["front.png","front_left.png","front_right.png","front_top.png","rear.png","rear_left.png","rear_right.png","rear_top.png"]},"ar720":{"org":"AR720_pic","img":["front.png","front_left.png","front_right.png","front_top.png","rear.png","rear_left.png","rear_right.png","rear_top.png"]},"asg5303":{"org":"ASG5303_pic","img":["front.png","front_left.png","front_right.png","front_top.png","left.png","rear.png","rear_left.png","rear_right.png","rear_top.png","right.png"]},"airengine5760-10":{"org":"AirEngine5760-10_pic","img":["bottom.png","front_left.png","front_right.png","front_top.png","rear_top.png","top.png"]},"airengine5760-22wd":{"org":"AirEngine5760-22WD_pic","img":["bottom.png","front.png","front_left.png","front_right.png","rear_bottom.png","rear_top.png","top.png"]},"airengine5760-22w":{"org":"AirEngine5760-22W_pic","img":["bottom.png","front.png","front_left.png","front_right.png","rear_bottom.png","rear_top.png","top.png"]},"airengine5760-51":{"org":"AirEngine5760-51_pic","img":["bottom.png","front.png","front_left.png","front_right.png","front_top.png","front_top_2.png","rear_top.png","top.png"]},"airengine5761-10wd":{"org":"AirEngine5761-10WD_pic","img":["front_bottom.png","front_top.png","top.png"]},"airengine5761-10w":{"org":"AirEngine5761-10W_pic","img":["front_bottom.png","front_top.png","top.png"]},"airengine5761-11wd":{"org":"AirEngine5761-11WD_pic","img":["front.png","front_bottom.png","front_left.png","front_right.png","rear.png","rear_bottom.png"]},"airengine5761-11w":{"org":"AirEngine5761-11W_pic","img":["front.png","front_bottom.png","front_left.png","front_right.png","rear.png","rear_bottom.png"]},"airengine5761-11":{"org":"AirEngine5761-11_pic","img":["front.png","front_bottom.png","front_left.png","front_right.png","front_top.png","rear.png","rear_top.png"]},"airengine5761-12w":{"org":"AirEngine5761-12W_pic","img":["front.png","front_bottom.png","front_left.png","front_right.png","rear.png","rear_bottom.png"]},"airengine5761-21":{"org":"AirEngine5761-21_pic","img":["front.png","front_bottom.png","front_left.png","front_right.png","front_top.png","rear.png","rear_top.png"]},"airengine5761r-11":{"org":"AirEngine5761R-11_pic","img":["bottom.png","front.png","front_left.png","front_right.png","rear.png","rear_top.png","top.png"]},"airengine5761rs-11":{"org":"AirEngine5761RS-11_pic","img":["bottom.png","front.png","front_left.png","front_right.png","rear.png","rear_top.png","top.png"]},"airengine5761s-10w":{"org":"AirEngine5761S-10W_pic","img":["front_bottom.png","front_top.png","top.png"]},"airengine5761s-11w":{"org":"AirEngine5761S-11W_pic","img":["front.png","front_bottom.png","front_left.png","front_right.png","rear.png","rear_bottom.png"]},"airengine5761s-11":{"org":"AirEngine5761S-11_pic","img":["front.png","front_bottom.png","front_left.png","front_right.png","front_top.png","rear.png","rear_top.png"]},"airengine5761s-12":{"org":"AirEngine5761S-12_pic","img":["front.png","front_bottom.png","front_left.png","front_right.png","front_top.png","rear.png","rear_top.png"]},"airengine5761s-13":{"org":"AirEngine5761S-13_pic","img":["front.png","front_bottom.png","front_left.png","front_right.png","front_top.png","rear.png","rear_top.png"]},"airengine5761s-21":{"org":"AirEngine5761S-21_pic","img":["front.png","front_bottom.png","front_left.png","front_right.png","front_top.png","rear.png","rear_top.png"]},"airengine6760-51ei":{"org":"AirEngine6760-51EI_pic","img":["front_left.png","front_right.png","front_top.png","left.png","rear_left.png","rear_right.png","rear_top.png","right.png","top.png"]},"airengine6761-21t":{"org":"AirEngine6761-21T_pic","img":["front.png","front_bottom.png","front_left.png","front_right.png","front_top.png","rear.png","rear_top.png"]},"airengine6761-21":{"org":"AirEngine6761-21_pic","img":["bottom.png","front.png","front_left.png","front_right.png","rear.png","rear_top.png","top.png"]},"airengine6761s-21t":{"org":"AirEngine6761S-21T_pic","img":["front.png","front_bottom.png","front_left.png","front_right.png","front_top.png","rear.png","rear_top.png"]},"airengine6761s-21":{"org":"AirEngine6761S-21_pic","img":["bottom.png","front.png","front_left.png","front_right.png","rear.png","rear_top.png","top.png"]},"airengine8760-x1-pro":{"org":"AirEngine8760-X1-PRO_pic","img":["bottom.png","front.png","front_left.png","front_right.png","front_top.png","front_top_2.png","rear_top.png","top.png"]},"airengine9700-m1":{"org":"AirEngine9700-M1_pic","img":["front.png","front_left.png","front_right.png","front_top.png","left.png","rear.png","rear_top.png","right.png"]},"airengine9700-m":{"org":"AirEngine9700-M_pic","img":["front.png","front_left.png","front_right.png","front_top.png","left.png","rear.png","rear_top.png","right.png"]},"airengine9700d-m":{"org":"AirEngine9700D-M_pic","img":["front.png","front_left.png","front_right.png","front_top.png","rear.png","rear_top.png"]},"antiddos12004":{"org":"AntiDDoS12004_pic","img":["front.png","front_left.png","front_right.png","front_top.png","rear.png"]},"antiddos1820":{"org":"AntiDDoS1820_pic","img":["front.png","front_left.png","front_top.png"]},"antiddos8030":{"org":"AntiDDoS8030_pic","img":["01-Front.png","02-Front_looking_down.png","03-Front_left_down.png","04-Front_right_down.png","08-Rear_looking_down.png","09-Rear_left_down.png","10-Rear_right_down.png"]},"ce12804s":{"org":"CE12804S_pic","img":["01-Front.png","02-Front_looking_down.png","03-Front_left.png","05-Front_right.png","07-Rear.png","09-Rear_left_looking_down.png","10-Rear_right_looking_down.png","11-Left_side.png","12-Right_side.png"]},"ce16804":{"org":"CE16804_pic","img":["front.png","front_left.png","front_right.png","front_top.png","left.png","rear.png","rear_left.png","rear_right.png","right.png"]},"ce5850-48t4s2q-hi":{"org":"CE5850-48T4S2Q-HI_pic","img":["01.png","02.png","03.png","04.png","07.png","08.png"]},"ce6850u-24s2q-hi":{"org":"CE6850U-24S2Q-HI_pic","img":["01.png","02.png","03.png","04.png","08.png","09.png"]},"ce6860-san":{"org":"CE6860-SAN_pic","img":["front.png","front_left.png","front_right.png","front_top.png","rear.png","rear_top.png"]},"ce8860-4c-ei":{"org":"CE8860-4C-EI_pic","img":["IMG_6544.png","IMG_6546.png","IMG_6547.png","IMG_6550.png","IMG_6552.png","IMG_6554.png"]},"ce9860-4c-ei":{"org":"CE9860-4C-EI_pic","img":["front.png","front_left.png","front_right.png","front_top.png","rear.png","rear_top.png"]},"es0w2psa0150":{"org":"ES0W2PSA0150_S_pic","img":["01.png","02.png","03.png","04.png"]},"et1d2fw00s00":{"org":"ET1D2FW00S00_S_pic","img":["01.png","02.png","03.png","04.png"]},"et1d2fw00s01":{"org":"ET1D2FW00S01_S_pic","img":["01.png","02.png","03.png","04.png"]},"et1d2fw00s02":{"org":"ET1D2FW00S02_S_pic","img":["01.png","02.png","03.png","04.png"]},"ips6585f":{"org":"IPS6585F_pic","img":["front.png","front_left.png","front_right.png","front_top.png","rear.png","rear_left.png","rear_right.png","rear_top.png"]},"me60-x3":{"org":"ME60-X3_pic","img":["front_top_ME60-X3-AC.png","front_top_ME60-X3-DC.png"]},"ne20e":{"org":"NE20E_S8A_pic","img":["front_NE20E_S8A_AC.png","front_NE20E_S8A_DC.png","front_letf_NE20E_S8A_AC.png","front_letf_NE20E_S8A_DC.png"]},"ne40e-x8":{"org":"NE40E-X8_pic","img":["front_left_NE40E-X8.png"]},"ne40e":{"org":"NE40E_M2K_pic","img":["front_top_02351OTH_NE40E_M2K_DC.png","front_top_02351OTJ_NE40E_M2K_AC.png"]},"ne5000e":{"org":"NE5000E_X16_pic","img":["front_left_NE5000E_X16.png"]},"ne9000":{"org":"ne9000_cx6600_dcpem_pic","img":["front_ne9000_cx6600_dcpem.png"]},"netengine":{"org":"NetEngine_8000_M6K_pic","img":["front_NetEngine_8000_M6K_AC.png","front_NetEngine_8000_M6K_DC.png","front_left_NetEngine_8000_M6K_AC.png","front_left_NetEngine_8000_M6K_DC.png","front_right_NetEngine_8000_M6K_AC.png","front_right_NetEngine_8000_M6K_DC.png","front_top_NetEngine_8000_M6K_AC.png","front_top_NetEngine_8000_M6K_DC.png"]},"optix ptn 7900e-12":{"org":"OptiX PTN 7900E-12_pic","img":["front.png"]},"optix ptn 905e":{"org":"OptiX PTN 905E_pic","img":["front_top.png"]},"pac-350wa-b":{"org":"PAC-350WA-B_S_pic","img":["01.png","02.png","03.png","04.png"]},"pac-600wa-b":{"org":"PAC-600WA-B_S_pic","img":["01.png","02.png","03.png","04.png"]},"pdc-350wa-b":{"org":"PDC-350WA-B_S_pic","img":["01.png","02.png","03.png","04.png"]},"r250d":{"org":"R250D_pic","img":["01.png","02.png","03.png","04.png","05.png","06.png","07.png"]},"r251d":{"org":"R251D_pic","img":["buttom.png","front_left.png","front_right.png","front_top.png","rear_top.png","right.png","stand_left.png","stand_right.png","top.png"]},"r450d":{"org":"R450D_pic","img":["bottom.png","front.png","front_left.png","front_right.png","front_top.png","rear_top.png","top.png"]},"ru-5g-101":{"org":"RU-5G-101_pic","img":["front.png","front_left.png","front_right.png","front_top.png","left.png","right.png"]},"s12700e-4":{"org":"S12700E-4_pic","img":["front.png","front_HD.png","front_left.png","front_left_HD.png","front_right.png","front_right_HD.png","front_top.png","front_top_HD.png","rear_top.png","rear_top_HD.png"]},"s12708":{"org":"S12708_pic","img":["01.png","02.png","03.png","04.png","IMG_7155.png","IMG_7160.png"]},"s1720-28gwr-4p":{"org":"S1720-28GWR-4P_pic","img":["front.png","front_left.png","front_right.png","front_top.png","rear.png","rear_top.png"]},"s200-8t4s":{"org":"S200-8T4S_pic","img":["front.png","front_left.png","front_right.png","front_top.png","rear.png","rear_top.png"]},"s2730s-s8ft4s-a":{"org":"S2730S-S8FT4S-A_pic","img":["front.png","front_left.png","front_right.png","front_top.png","rear.png","rear_top.png"]},"s2750-28tp-ei-ac":{"org":"S2750-28TP-EI-AC_pic","img":["01.png","02.png","03.png","04.png","07.png","08.png"]},"s300-8t4s":{"org":"S300-8T4S_pic","img":["front.png","front_left.png","front_right.png","front_top.png","rear.png","rear_top.png"]},"s500-8t4s":{"org":"S500-8T4S_pic","img":["front.png","front_left.png","front_right.png","front_top.png","rear.png","rear_top.png"]},"s5720-36c-ei-ac":{"org":"S5720-36C-EI-AC_pic","img":["01.png","02.png","03.png","04.png","07.png","08.png"]},"s5732-h48xum2cc":{"org":"S5732-H48XUM2CC_pic","img":["front.png","front_HD.png","front_left.png","front_left_HD.png","front_right.png","front_right_HD.png","front_top.png","front_top_HD.png","rear_top.png","rear_top_HD.png"]},"s5736-s24um4xc":{"org":"S5736-S24UM4XC_pic","img":["front.png","front_left.png","front_right.png","front_top.png","rear.png","rear_top.png"]},"s5736-s48s4x-a":{"org":"S5736-S48S4X-A_pic","img":["front.png","front_left.png","front_right.png","front_top.png","rear.png","rear_top.png"]},"s628-e":{"org":"S628-E_pic","img":["IMG_1909.png","IMG_1910.png","IMG_1911.png","IMG_2009.png","IMG_2262.png"]},"s6700-24-ei":{"org":"S6700-24-EI_pic","img":["01.png","02.png","03.png","04.png","08.png"]},"s6730-h28y4c":{"org":"S6730-H28Y4C_pic","img":["front.png","front_HD.png","front_left.png","front_left_HD.png","front_right.png","front_right_HD.png","front_top.png","front_top_HD.png","rear_top.png"]},"s7703":{"org":"S7703_pic","img":["02.png","03.png","04.png","08.png"]},"s7706":{"org":"S7706_PoE_pic","img":["front_top.png","rear_top.png"]},"s7905":{"org":"S7905_pic","img":["01.png","02.png","03.png","04.png","08.png"]},"sig9800":{"org":"SIG9800_X16A_pic","img":["front_top_SIG9800_X16A.png"]},"uma1520e":{"org":"UMA1520E_pic","img":["front.png","front_left.png","front_right.png","front_top.png","rear.png"]},"usg12004":{"org":"USG12004_pic","img":["front.png","front_left.png","front_right.png","front_top.png","rear.png"]},"usg6307e":{"org":"USG6307E_pic","img":["front.png","front_top.png","rear_left.png","rear_top.png"]},"usg6510e":{"org":"USG6510E_pic","img":["front.png","front_top.png","rear_left.png","rear_top.png"]},"usg6525e":{"org":"USG6525E_pic","img":["front.png","front_left.png","front_right.png","front_top.png","rear.png","rear_top.png"]},"usg6610e":{"org":"USG6610E_pic","img":["front.png","front_left.png","front_right.png","front_top.png","rear.png","rear_left.png","rear_right.png","rear_top.png"]},"usg6615f":{"org":"USG6615F_pic","img":["front.png","front_left.png","front_right.png","front_top.png","rear.png","rear_left.png","rear_right.png","rear_top.png"]},"usg6712e":{"org":"USG6712E_pic","img":["front.png","front_left.png","front_right.png","front_top.png","rear.png","rear_top.png"]},"usg9520":{"org":"USG9520_pic","img":["01-Front.png","02-Front_looking_down.png","03-Front_left_down.png","04-Front_right_down.png","05-Left_side.png","06-Right_side.png","07-Rear.png","08-Rear_looking_down.png","09-Rear_left_down.png","10-Rear_right_down.png"]},"vscan1506":{"org":"VSCAN1506_pic","img":["front.png","front_left.png","front_right.png","front_top.png","rear.png","rear_left.png","rear_right.png","rear_top.png"]},"waf5110":{"org":"WAF5110_pic","img":["front.png","front_left.png","front_right.png","front_top.png","left.png","rear.png","rear_left.png","rear_right.png","rear_top.png","right.png"]},"zh":{"org":"zh_NetEngine_8000_M6_pic","img":["front_NetEngine_8000_M6_AC.png","front_NetEngine_8000_M6_DC.png","front_left_NetEngine_8000_M6_AC.png","front_left_NetEngine_8000_M6_DC.png","front_right_NetEngine_8000_M6_AC.png","front_right_NetEngine_8000_M6_DC.png","front_top_NetEngine_8000_M6_AC.png","front_top_NetEngine_8000_M6_DC.png","rear_NetEngine_8000_M6_AC.png"]},"mstp":{"org":"mstp_ucxe_pic","img":["ucxe_front.png","ucxe_side01.png","ucxe_side02.png"]},"ne05e":{"org":"ne05e_sq_pic","img":["front_top_ne05e_sq.png"]},"ne08e":{"org":"ne08e_s9_pic","img":["front_ne08e_s9_AC.png","front_top_ne08e_s9_DC.png"]},"wdm":{"org":"wdm_xfp_pic","img":["XFP.png"]}}